{
  "LCC1": [
    {
      "acronym": "LCC1",
      "meaning": "Laboratório de Ciência da Computação 1",
      "type": "Sala",
      "entry": "Laboratório de Ciência da Computação 1",
      "examples": []
    }
  ],
  "LCC2": [
    {
      "acronym": "LCC2",
      "meaning": "Laboratório de Ciência da Computação 2",
      "type": "Sala",
      "entry": "Laboratório de Ciência da Computação 2",
      "examples": []
    }
  ],
  "LCC3": [
    {
      "acronym": "LCC3",
      "meaning": "Laboratório de Ciência da Computação 3",
      "type": "Sala",
      "entry": "Laboratório de Ciência da Computação 3",
      "examples": []
    }
  ]
}
